[
  {
    "alpha": 50.0,
    "backgroundColor": "-16777216",
    "colors": "-65536;-256;-16711936;-16711681;-16776961;-65281",
    "cross": 50.0,
    "iid": 1,
    "isThemeDefault": true,
    "name": "RGB",
    "preview_thumb": "https://imgrgbkeyboard.s3.eu-central-1.amazonaws.com/rgbkey_theme/RGB.png",
    "preview": "https://imgrgbkeyboard.s3.eu-central-1.amazonaws.com/rgb_thumb_theme/RGB.png",
    "radius": 1.9,
    "range": 50.0,
    "speed": 50.0,
    "strokeWidth": 40.0,
    "style": "style_stroke",
    "styleLed": 1,
    "font" : "fonts/segoeui.TTF",
    "background" : "default"
  },
  {
    "alpha": 50.0,
    "backgroundColor": "-16777216",
    "colors": "-65536;-256;-16711936;-16711681;-16776961;-65281",
    "cross": 50.0,
    "iid": 2,
    "isThemeDefault": true,
    "name": "Round",
    "preview_thumb": "https://imgrgbkeyboard.s3.eu-central-1.amazonaws.com/rgbkey_theme/Round.png",
    "preview": "https://imgrgbkeyboard.s3.eu-central-1.amazonaws.com/rgb_thumb_theme/Round.png",
    "radius": 2.0,
    "range": 50.0,
    "speed": 50.0,
    "strokeWidth":  1.0,
    "style": "style_fill",
    "styleLed": 1,
    "font" : "fonts/segoeui.TTF",
    "background" : "default"
  },
  {
    "alpha": 50.0,
    "backgroundColor": "-16777216",
    "colors": "-65536;-256;-16711936;-16711681;-16776961;-65281",
    "cross": 50.0,
    "iid": 3,
    "isThemeDefault": true,
    "name": "Slow",
    "preview_thumb": "https://imgrgbkeyboard.s3.eu-central-1.amazonaws.com/rgbkey_theme/Slow.png",
    "preview": "https://imgrgbkeyboard.s3.eu-central-1.amazonaws.com/rgb_thumb_theme/Slow.png",
    "radius": 1.0,
    "range": 50.0,
    "speed": 50.0,
    "strokeWidth": 1.0,
    "style": "style_stroke",
    "styleLed": 2,
    "font" : "fonts/segoeui.TTF",
    "background" : "default"
  }
]